dlt/__init__.py
dlt/adapter.py
dlt/protocol.py
logging_dlt-1.0.0.dist-info/LICENSE
logging_dlt-1.0.0.dist-info/METADATA
logging_dlt-1.0.0.dist-info/WHEEL
logging_dlt-1.0.0.dist-info/top_level.txt
logging_dlt-1.0.0.dist-info/RECORD
