Metadata-Version: 2.1
Name: logging-dlt
Version: 1.0.0
Summary: A python logging adapter for diagnostic log and trace protocol.
Author-email: Patrick Menschel <menschel.p@posteo.de>
Project-URL: Homepage, https://gitlab.com/menschel/logging-dlt
Project-URL: Bug Tracker, https://gitlab.com/menschel/logging-dlt/issues
Classifier: Programming Language :: Python :: 3
Classifier: Development Status :: 5 - Production/Stable
Classifier: License :: OSI Approved :: GNU General Public License v3 or later (GPLv3+)
Classifier: License :: Free for non-commercial use
Classifier: Intended Audience :: Developers
Classifier: Topic :: Scientific/Engineering
Classifier: Topic :: Software Development :: Embedded Systems
Requires-Python: >=3.11
License-File: LICENSE
Requires-Dist: socketcan
